is_this_journal_predatory/__init__.py
is_this_journal_predatory/predatory_journals.json
is_this_journal_predatory-0.0.2.dist-info/LICENSE
is_this_journal_predatory-0.0.2.dist-info/METADATA
is_this_journal_predatory-0.0.2.dist-info/WHEEL
is_this_journal_predatory-0.0.2.dist-info/top_level.txt
is_this_journal_predatory-0.0.2.dist-info/RECORD
