Metadata-Version: 2.1
Name: is-this-journal-predatory
Version: 0.0.2
Summary: Check whether a journal is listed in Beall's List from within Python.
Home-page: https://github.com/bganglia/is_this_journal_predatory/blob/master/check_predatory.py
Author: bganglia
Author-email: bganglia892@gmail.com
License: UNKNOWN
Platform: UNKNOWN
Requires-Python: >=3.6
